datastore/__init__.py
datastore/mongodb.py
justice/__init__.py
justice/justice.py
justice/session.py
justice/statistic.py
justice/wallet.py
justice_augment_python_sdk-0.3.1.dist-info/LICENSE
justice_augment_python_sdk-0.3.1.dist-info/METADATA
justice_augment_python_sdk-0.3.1.dist-info/WHEEL
justice_augment_python_sdk-0.3.1.dist-info/top_level.txt
justice_augment_python_sdk-0.3.1.dist-info/RECORD
