Metadata-Version: 2.1
Name: justice-augment-python-sdk
Version: 0.3.1
Summary: Python SDK for Justice Augment
Home-page: https://bitbucket.org/accelbyte/justice-augment-python-sdk
Author: Bahrunnur
Author-email: bahrunnur@accelbyte.io
License: Apache 2.0
Platform: UNKNOWN
Classifier: Intended Audience :: Developers
Classifier: Programming Language :: Python
Classifier: Programming Language :: Python :: 3
Classifier: Programming Language :: Python :: 3.8
Requires-Dist: requests
Requires-Dist: pymongo (==3.10.1)
